opensearch_log/__about__.py
opensearch_log/__init__.py
opensearch_log/base_handler.py
opensearch_log/cloudwatch_handler.py
opensearch_log/json_log.py
opensearch_log/opensearch_handler.py
opensearch_log/opensearch_serializer.py
opensearch_log/stdout_handler.py
opensearch_log-1.3.1.dist-info/METADATA
opensearch_log-1.3.1.dist-info/WHEEL
opensearch_log-1.3.1.dist-info/licenses/LICENSE.txt
opensearch_log-1.3.1.dist-info/RECORD
