Metadata-Version: 2.1
Name: opensearch-log
Version: 1.3.1
Summary: A Python logging handler for efficient and reliable direct log transmission to OpenSearch, CloudWatch with additional fields.
Project-URL: Homepage, https://andgineer.github.io/opensearch-log/
Project-URL: Documentation, https://andgineer.github.io/opensearch-log/
Author-email: Andrey Sorokin <andrey@sorokin.engineer>
License: Copyright (c) 2021 Andrey Sorokin <andrey@sorokin.engineer>
License-File: LICENSE.txt
Keywords: aws,cloudwatch,elasticsearch,kibana,log,log-handler,logging,opensearch
Classifier: License :: OSI Approved :: MIT License
Classifier: Operating System :: OS Independent
Classifier: Programming Language :: Python :: 3
Requires-Python: >=3.9
Requires-Dist: python-json-logger
Provides-Extra: cloudwatch
Requires-Dist: boto3; extra == 'cloudwatch'
Provides-Extra: opensearch
Requires-Dist: boto3; extra == 'opensearch'
Requires-Dist: opensearch-py; extra == 'opensearch'
